classyDict/__init__.py
classyDict/classy_dict.py
classydict-0.1.3.dist-info/METADATA
classydict-0.1.3.dist-info/WHEEL
classydict-0.1.3.dist-info/top_level.txt
classydict-0.1.3.dist-info/RECORD
